pihole_mcp_server/__init__.py
pihole_mcp_server/cli.py
pihole_mcp_server/credential_manager.py
pihole_mcp_server/pihole_client.py
pihole_mcp_server/server.py
pihole_mcp_server-0.1.1.dist-info/METADATA
pihole_mcp_server-0.1.1.dist-info/WHEEL
pihole_mcp_server-0.1.1.dist-info/entry_points.txt
pihole_mcp_server-0.1.1.dist-info/licenses/LICENSE
pihole_mcp_server-0.1.1.dist-info/RECORD
