Metadata-Version: 2.4
Name: pihole-mcp-server
Version: 0.1.1
Summary: MCP server for Pi-hole DNS server interactions
Project-URL: Homepage, https://github.com/brettbergin/pihole-mcp-server
Project-URL: Documentation, https://github.com/brettbergin/pihole-mcp-server#readme
Project-URL: Repository, https://github.com/brettbergin/pihole-mcp-server.git
Project-URL: Issues, https://github.com/brettbergin/pihole-mcp-server/issues
Author-email: Brett Bergin <brettberginbc@yahoo.com>
License: MIT
License-File: LICENSE
Keywords: cursor,dns,mcp,pihole,server
Classifier: Development Status :: 4 - Beta
Classifier: Intended Audience :: Developers
Classifier: License :: OSI Approved :: MIT License
Classifier: Operating System :: OS Independent
Classifier: Programming Language :: Python :: 3
Classifier: Programming Language :: Python :: 3.10
Classifier: Programming Language :: Python :: 3.11
Classifier: Programming Language :: Python :: 3.12
Classifier: Programming Language :: Python :: 3.13
Classifier: Topic :: Software Development :: Libraries :: Python Modules
Classifier: Topic :: System :: Networking
Requires-Python: >=3.10
Requires-Dist: click>=8.0.0
Requires-Dist: cryptography>=3.4.8
Requires-Dist: keyring>=24.0.0
Requires-Dist: mcp>=1.0.0
Requires-Dist: pydantic>=2.0.0
Requires-Dist: requests>=2.28.0
Requires-Dist: rich>=13.0.0
Requires-Dist: typing-extensions>=4.0.0
Provides-Extra: dev
Requires-Dist: black>=23.0.0; extra == 'dev'
Requires-Dist: freezegun>=1.2.0; extra == 'dev'
Requires-Dist: isort>=5.0.0; extra == 'dev'
Requires-Dist: mypy>=1.0.0; extra == 'dev'
Requires-Dist: pytest-asyncio>=0.21.0; extra == 'dev'
Requires-Dist: pytest-cov>=4.0.0; extra == 'dev'
Requires-Dist: pytest-mock>=3.10.0; extra == 'dev'
Requires-Dist: pytest>=7.0.0; extra == 'dev'
Requires-Dist: responses>=0.24.0; extra == 'dev'
Requires-Dist: ruff>=0.1.0; extra == 'dev'
